pojw/__init__.py
pojw/ojw.py
pojw-0.0.8.dist-info/LICENSE
pojw-0.0.8.dist-info/METADATA
pojw-0.0.8.dist-info/WHEEL
pojw-0.0.8.dist-info/top_level.txt
pojw-0.0.8.dist-info/RECORD
